{"nodes": [{"id": "tests_test_phase5_evaluation_py", "label": "test_phase5_evaluation.py", "file_type": "code", "source_file": "tests\\test_phase5_evaluation.py", "source_location": "L1"}, {"id": "test_phase5_evaluation_test_percentile_basic", "label": "test_percentile_basic()", "file_type": "code", "source_file": "tests\\test_phase5_evaluation.py", "source_location": "L8"}, {"id": "test_phase5_evaluation_test_relevance_score_bounds", "label": "test_relevance_score_bounds()", "file_type": "code", "source_file": "tests\\test_phase5_evaluation.py", "source_location": "L14"}, {"id": "test_phase5_evaluation_test_explanation_quality_scoring", "label": "test_explanation_quality_scoring()", "file_type": "code", "source_file": "tests\\test_phase5_evaluation.py", "source_location": "L22"}], "edges": [{"source": "tests_test_phase5_evaluation_py", "target": "src_phase_5_evaluation_service_evaluation", "relation": "imports_from", "confidence": "EXTRACTED", "source_file": "tests\\test_phase5_evaluation.py", "source_location": "L1", "weight": 1.0}, {"source": "tests_test_phase5_evaluation_py", "target": "test_phase5_evaluation_test_percentile_basic", "relation": "contains", "confidence": "EXTRACTED", "source_file": "tests\\test_phase5_evaluation.py", "source_location": "L8", "weight": 1.0}, {"source": "tests_test_phase5_evaluation_py", "target": "test_phase5_evaluation_test_relevance_score_bounds", "relation": "contains", "confidence": "EXTRACTED", "source_file": "tests\\test_phase5_evaluation.py", "source_location": "L14", "weight": 1.0}, {"source": "tests_test_phase5_evaluation_py", "target": "test_phase5_evaluation_test_explanation_quality_scoring", "relation": "contains", "confidence": "EXTRACTED", "source_file": "tests\\test_phase5_evaluation.py", "source_location": "L22", "weight": 1.0}]}